markdown_view/__init__.py
markdown_view/apps.py
markdown_view/checks.py
markdown_view/constants.py
markdown_view/loaders.py
markdown_view/markdown_extensions.py
markdown_view/models.py
markdown_view/views.py
markdown_view/templates/markdown_view/markdown.html
django_markdown_view-0.0.5.dist-info/LICENSE
django_markdown_view-0.0.5.dist-info/METADATA
django_markdown_view-0.0.5.dist-info/WHEEL
django_markdown_view-0.0.5.dist-info/top_level.txt
django_markdown_view-0.0.5.dist-info/RECORD
