Metadata-Version: 2.1
Name: django-markdown-view
Version: 0.0.5
Summary: Serve .md pages as Django views.
Home-page: http://github.com/rgs258/django-markdown-view
Author: Ryan J. Sullivan
Author-email: ryanj@ryanjsullivan.com
License: BSD
Keywords: django,markdown,markdown view,md
Platform: UNKNOWN
Classifier: Development Status :: 3 - Alpha
Classifier: Framework :: Django :: 2
Classifier: Framework :: Django :: 3
Classifier: Framework :: Django :: 4
Classifier: Framework :: Django
Classifier: Intended Audience :: Developers
Classifier: License :: OSI Approved :: BSD License
Classifier: Operating System :: OS Independent
Classifier: Programming Language :: Python
Classifier: Topic :: Internet :: WWW/HTTP :: Dynamic Content
Classifier: Programming Language :: Python :: 3
Classifier: Programming Language :: Python :: 3.7
Classifier: Programming Language :: Python :: 3.8
Classifier: Programming Language :: Python :: 3.9
Classifier: Programming Language :: Python :: 3.10
Requires-Dist: django (>=2.2)
Requires-Dist: markdown (>=3.2)
